redash_toolbelt/__init__.py
redash_toolbelt/client.py
redash_toolbelt/date_ranges.py
redash_toolbelt/docs/redash-migrate/README.md
redash_toolbelt/examples/__init__.py
redash_toolbelt/examples/clone_dashboard_and_queries.py
redash_toolbelt/examples/find_table_names.py
redash_toolbelt/examples/gdpr_scrub.py
redash_toolbelt/examples/migrate.py
redash_toolbelt/examples/query_export.py
redash_toolbelt/examples/refresh_dashboard.py
redash_toolbelt/examples/refresh_query.py
redash_toolbelt-0.1.9.dist-info/entry_points.txt
redash_toolbelt-0.1.9.dist-info/LICENSE
redash_toolbelt-0.1.9.dist-info/WHEEL
redash_toolbelt-0.1.9.dist-info/METADATA
redash_toolbelt-0.1.9.dist-info/RECORD
