Metadata-Version: 2.1
Name: redash-toolbelt
Version: 0.1.9
Summary: Redash API client and tools to manage your instance.
Home-page: https://github.com/getredash/redash-toolbelt
License: BSD-2-Clause
Author: Redash Maintainers
Requires-Python: >=3.6,<4.0
Classifier: License :: OSI Approved :: BSD License
Classifier: Programming Language :: Python :: 3
Classifier: Programming Language :: Python :: 3.10
Classifier: Programming Language :: Python :: 3.6
Classifier: Programming Language :: Python :: 3.7
Classifier: Programming Language :: Python :: 3.8
Classifier: Programming Language :: Python :: 3.9
Requires-Dist: click (>=8.0.3,<9.0.0)
Requires-Dist: requests (>=2.22.0,<3.0.0)
Project-URL: Repository, https://github.com/getredash/redash-toolbelt
